python_snappy/__init__.py
python_snappy/exceptions.py
python_snappy/snappy.py
python_snappy_pure-0.2.0.dist-info/METADATA
python_snappy_pure-0.2.0.dist-info/WHEEL
python_snappy_pure-0.2.0.dist-info/licenses/LICENSE
python_snappy_pure-0.2.0.dist-info/RECORD
