Metadata-Version: 2.4
Name: python-snappy-pure
Version: 0.2.0
Summary: Pure Python Snappy compression and decompression
Project-URL: Homepage, https://github.com/Valmarelox/python-snappy
Project-URL: Repository, https://github.com/Valmarelox/python-snappy
License-Expression: MIT
License-File: LICENSE
Keywords: compression,decompression,snappy
Classifier: Development Status :: 4 - Beta
Classifier: Intended Audience :: Developers
Classifier: License :: OSI Approved :: MIT License
Classifier: Programming Language :: Python :: 3
Classifier: Programming Language :: Python :: 3.10
Classifier: Programming Language :: Python :: 3.11
Classifier: Programming Language :: Python :: 3.12
Classifier: Programming Language :: Python :: 3.13
Classifier: Topic :: System :: Archiving :: Compression
Requires-Python: >=3.10
Provides-Extra: test
Requires-Dist: pytest>=7.0; extra == 'test'
Requires-Dist: python-snappy>=0.6; extra == 'test'
